{"expireTime":9007200984307526000,"key":"transformer-remark-markdown-html-ast-be689feebb6cd0631addc3a7a4586362-gatsby-remark-external-linksgatsby-remark-imagesgatsby-remark-code-titlesgatsby-remark-prismjs-","val":{"type":"root","children":[{"type":"element","tagName":"p","properties":{},"children":[{"type":"text","value":"Project 4 under HTML-CSS Suven Coding Internship","position":{"start":{"line":2,"column":1,"offset":1},"end":{"line":2,"column":49,"offset":49}}}],"position":{"start":{"line":2,"column":1,"offset":1},"end":{"line":2,"column":49,"offset":49}}}],"position":{"start":{"line":1,"column":1,"offset":0},"end":{"line":3,"column":1,"offset":50}}}}